LICENSE.txt
MANIFEST.in
README.rst
release-history.rst
requirements.txt
setup.py
autocompvar/__init__.py
autocompvar/base.py
autocompvar/exc.py
autocompvar/helpers.py
autocompvar/metadata.py
autocompvar/name_convention.py
autocompvar/zzz_manual_install.py
autocompvar.egg-info/PKG-INFO
autocompvar.egg-info/SOURCES.txt
autocompvar.egg-info/dependency_links.txt
autocompvar.egg-info/requires.txt
autocompvar.egg-info/top_level.txt
autocompvar/__pycache__/__init__.cpython-33.pyc
autocompvar/__pycache__/exc.cpython-33.pyc
autocompvar/__pycache__/helpers.cpython-33.pyc
autocompvar/__pycache__/metadata.cpython-33.pyc
autocompvar/__pycache__/name_convention.cpython-33.pyc
autocompvar/pkg/__init__.py
autocompvar/pkg/class_metadata.py
autocompvar/pkg/nameddict.py
autocompvar/pkg/six.py
autocompvar/pkg/__pycache__/__init__.cpython-33.pyc
autocompvar/pkg/__pycache__/nameddict.cpython-33.pyc
autocompvar/pkg/__pycache__/six.cpython-33.pyc
autocompvar/templates/__init__.py
autocompvar/templates/code.txt
autocompvar/templates/def_all_class.txt
autocompvar/templates/def_class.txt
autocompvar/templates/__pycache__/__init__.cpython-33.pyc